{
    "name":"cbmigrations",
    "version":"2.0.0",
    "author":"Eric Peterson",
    "location":"elpete/cbmigrations#v1.1.0",
    "homepage":"https://github.com/elpete/cbmigrations",
    "documentation":"",
    "repository":{
        "type":"git",
        "URL":"https://github.com/elpete/cbmigrations"
    },
    "bugs":"https://github.com/elpete/cbmigrations/issues",
    "slug":"cbmigrations",
    "shortDescription":"Keep track of database migrations using ColdBox",
    "type":"modules",
    "keywords":[
        "database",
        "migrations",
        "coldbox"
    ],
    "private":false,
    "license":[
        {
            "type":"MIT",
            "URL":"https://raw.githubusercontent.com/elpete/cbmigrations/master/LICENSE"
        }
    ],
    "scripts":{
        "postVersion":"package set location='elpete/cbmigrations#v`package version`'",
        "postPublish":"!git push && !git push --tags"
    },
    "ignore":[
        "**/.*",
        "test",
        "tests"
    ],
    "devDependencies":{
        "testbox":"^2.3.0+00044"
    },
    "installPaths":{
        "testbox":"testbox"
    }
}